<?xml version="1.0" encoding="utf-8"?>
<!DOCTYPE hibernate-mapping PUBLIC "-//Hibernate/Hibernate Mapping DTD 3.0//EN"
"http://hibernate.sourceforge.net/hibernate-mapping-3.0.dtd">
<!-- Generated 2018-7-4 12:26:08 by Hibernate Tools 3.5.0.Final -->
<hibernate-mapping>
    <class name="com.common.pojo.SlotStatus2" table="SlotStatus2" 
    	schema="dbo" catalog="room_manager_db">
        <id name="id" type="java.lang.Integer">
            <column name="id" />
            <generator class="increment" />
        </id>
        <property name="slotID" type="java.lang.Integer">
            <column name="slotID" />
        </property>
        <property name="slotStatus" type="java.lang.Boolean">
            <column name="slot_status" />
        </property>
        <property name="slotCardNum" type="java.lang.String">
            <column name="slot_card_num" length="20" />
        </property>
        <property name="powerStatus" type="java.lang.Boolean">
            <column name="power_status" />
        </property>
        <property name="serviceLight" type="java.lang.String">
            <column name="service_light" length="4" />
        </property>
        <property name="isDevOnline" type="java.lang.Boolean">
            <column name="is_dev_online" />
        </property>
        <property name="time" type="java.sql.Timestamp">
            <column name="time" length="23"/>
        </property>
    </class>
</hibernate-mapping>
